{
  "type": "FeatureCollection",
  "routes": [
    {
      "id": "B01",
      "name": "EDSA Carousel Northbound",
      "color": "#EF4444",
      "path": [
        [14.5547, 121.0339],
        [14.5710, 121.0350],
        [14.5870, 121.0380],
        [14.6044, 121.0408],
        [14.6194, 121.0467],
        [14.6350, 121.0430],
        [14.6480, 121.0420]
      ]
    },
    {
      "id": "B02",
      "name": "EDSA Carousel Southbound",
      "color": "#EF4444",
      "path": [
        [14.6480, 121.0420],
        [14.6350, 121.0435],
        [14.6194, 121.0467],
        [14.6044, 121.0408],
        [14.5870, 121.0395],
        [14.5710, 121.0365],
        [14.5547, 121.0339]
      ]
    },
    {
      "id": "B03",
      "name": "Ayala - Quiapo via España",
      "color": "#EF4444",
      "path": [
        [14.5547, 121.0244],
        [14.5620, 121.0180],
        [14.5720, 121.0120],
        [14.5820, 121.0060],
        [14.5920, 120.9990],
        [14.5995, 120.9842]
      ]
    },
    {
      "id": "B04",
      "name": "Fairview - Monumento",
      "color": "#EF4444",
      "path": [
        [14.7050, 121.0580],
        [14.6950, 121.0520],
        [14.6820, 121.0470],
        [14.6680, 121.0450],
        [14.6560, 121.0440]
      ]
    }
  ]
}
